Workbook

Sheet Summary
B1: Total | C1: =SUM(C3:C62) -> 417
B2: Group | C2: Count | E2: Cost | F2: Count
B3: {=_xlfn.UNIQUE(_xlfn._xlws.FILTER(Combined!G2:G1000,Combined!G2:G1000<>"",Combined!G2:G1000<>""))} -> Spiritual | C3: =COUNTIF(Combined!$G$2:$G$1065, Summary!B3) -> 28 | E3: {=_xlfn._xlws.SORT(_xlfn.UNIQUE(_xlfn._xlws.FILTER(Combined!D2:D1000,Combined!D2:D1000<>"",Combined!D2:D1000<>"")))} -> 0 | F3: =COUNTIF(Combined!$D$2:$D$1065, Summary!E3) -> 8
B4: Psychic | C4: =COUNTIF(Combined!$G$2:$G$1065, Summary!B4) -> 25 | E4: 25 | F4: =COUNTIF(Combined!$D$2:$D$1065, Summary!E4) -> 8
B5: Martial | C5: =COUNTIF(Combined!$G$2:$G$1065, Summary!B5) -> 27 | E5: 50 | F5: =COUNTIF(Combined!$D$2:$D$1065, Summary!E5) -> 2
B6: Alchemy | C6: =COUNTIF(Combined!$G$2:$G$1065, Summary!B6) -> 29 | E6: 100 | F6: =COUNTIF(Combined!$D$2:$D$1065, Summary!E6) -> 37
B7: Magic | C7: =COUNTIF(Combined!$G$2:$G$1065, Summary!B7) -> 28 | E7: 150 | F7: =COUNTIF(Combined!$D$2:$D$1065, Summary!E7) -> 32
B8: Eldritch | C8: =COUNTIF(Combined!$G$2:$G$1065, Summary!B8) -> 26 | E8: 175 | F8: =COUNTIF(Combined!$D$2:$D$1065, Summary!E8) -> 1
B9: Planar | C9: =COUNTIF(Combined!$G$2:$G$1065, Summary!B9) -> 24 | E9: 200 | F9: =COUNTIF(Combined!$D$2:$D$1065, Summary!E9) -> 112
B10: Physics | C10: =COUNTIF(Combined!$G$2:$G$1065, Summary!B10) -> 41 | E10: 250 | F10: =COUNTIF(Combined!$D$2:$D$1065, Summary!E10) -> 24
B11: General | C11: =COUNTIF(Combined!$G$2:$G$1065, Summary!B11) -> 98 | E11: 300 | F11: =COUNTIF(Combined!$D$2:$D$1065, Summary!E11) -> 63
B12: Stuff | C12: =COUNTIF(Combined!$G$2:$G$1065, Summary!B12) -> 58 | E12: 350 | F12: =COUNTIF(Combined!$D$2:$D$1065, Summary!E12) -> 13
B13: Powers | C13: =COUNTIF(Combined!$G$2:$G$1065, Summary!B13) -> 33 | E13: 400 | F13: =COUNTIF(Combined!$D$2:$D$1065, Summary!E13) -> 18
C14: =COUNTIF(Combined!$G$2:$G$1065, Summary!B14) -> 0 | E14: 450 | F14: =COUNTIF(Combined!$D$2:$D$1065, Summary!E14) -> 2
C15: =COUNTIF(Combined!$G$2:$G$1065, Summary!B15) -> 0 | E15: 500 | F15: =COUNTIF(Combined!$D$2:$D$1065, Summary!E15) -> 48
C16: =COUNTIF(Combined!$G$2:$G$1065, Summary!B16) -> 0 | E16: 550 | F16: =COUNTIF(Combined!$D$2:$D$1065, Summary!E16) -> 1
C17: =COUNTIF(Combined!$G$2:$G$1065, Summary!B17) -> 0 | E17: 600 | F17: =COUNTIF(Combined!$D$2:$D$1065, Summary!E17) -> 8
C18: =COUNTIF(Combined!$G$2:$G$1065, Summary!B18) -> 0 | E18: 750 | F18: =COUNTIF(Combined!$D$2:$D$1065, Summary!E18) -> 15
C19: =COUNTIF(Combined!$G$2:$G$1065, Summary!B19) -> 0 | E19: 800 | F19: =COUNTIF(Combined!$D$2:$D$1065, Summary!E19) -> 1
C20: =COUNTIF(Combined!$G$2:$G$1065, Summary!B20) -> 0 | E20: 900 | F20: =COUNTIF(Combined!$D$2:$D$1065, Summary!E20) -> 2
C21: =COUNTIF(Combined!$G$2:$G$1065, Summary!B21) -> 0 | E21: 1000 | F21: =COUNTIF(Combined!$D$2:$D$1065, Summary!E21) -> 16
C22: =COUNTIF(Combined!$G$2:$G$1065, Summary!B22) -> 0 | E22: 1200 | F22: =COUNTIF(Combined!$D$2:$D$1065, Summary!E22) -> 6
C23: =COUNTIF(Combined!$G$2:$G$1065, Summary!B23) -> 0
C24: =COUNTIF(Combined!$G$2:$G$1065, Summary!B24) -> 0
C25: =COUNTIF(Combined!$G$2:$G$1065, Summary!B25) -> 0
C26: =COUNTIF(Combined!$G$2:$G$1065, Summary!B26) -> 0
C27: =COUNTIF(Combined!$G$2:$G$1065, Summary!B27) -> 0
C28: =COUNTIF(Combined!$G$2:$G$1065, Summary!B28) -> 0
C29: =COUNTIF(Combined!$G$2:$G$1065, Summary!B29) -> 0
C30: =COUNTIF(Combined!$G$2:$G$1065, Summary!B30) -> 0
C31: =COUNTIF(Combined!$G$2:$G$1065, Summary!B31) -> 0
C32: =COUNTIF(Combined!$G$2:$G$1065, Summary!B32) -> 0
C33: =COUNTIF(Combined!$G$2:$G$1065, Summary!B33) -> 0
C34: =COUNTIF(Combined!$G$2:$G$1065, Summary!B34) -> 0
... C60: =COUNTIF(Combined!$G$2:$G$1065, Summary!B60) -> 0

Sheet Combined
A1: ID | B1: Name | C1: Description | D1: Cost | E1: Repeatable | F1: Dependency | G1: Group
A2: 0 | B2: Spiritual Energy | C2: The stuff that makes up souls. that undefinable thing that still defines everything. Everything makes it all the time, though you perhaps make more than usual. You are now able to manipulate it to your own ends | D2: 0 | E2: max | F2: 0 | G2: Spiritual
A3: 1 | B3: The Root of Meaning | C3: There is meaning to this world. Yet, if you ground all of existence into it's finest components and searched through it all, you would find none. It is this paradox that you now command, to be able to empower the very meaning that is born of form | D3: 300 | E3: 1 | F3: Spiritual Energy | G3: Spiritual
A4: 2 | B4: Divine Insight | C4: Gods Exist. Or do they? Born of belief yet having always existed, it is difficult to say if people created gods or gods created people. The answer to that dichotomy is the core to divinity - the end result of Meaning enforced upon existence through collective action. And that is a secret you now hold in your heart of hearts | D4: 300 | E4: 1 | F4: Spiritual Energy | G4: Spiritual
A5: 3 | B5: Sword Intent | C5: Or anything intent, really, you know how to imbue spiritual energy into items you craft giving them the beginnings of sentience. Though they will never develop any true sapience, they are born with 'instincts' regarding their proper use and will learn alongside their wielders. They can make their desires known to their operators and function better than they physically should, growing as their souls do. | D5: 300 | E5: 1 | F5: Spiritual Energy | G5: Spiritual
A6: 4 | B6: Spirits | C6: Not quite souls, but perhaps something along the way. Spiritual constructs with a degree of agency capable of carrying out specific tasks and acting in a specific manner are far simpler to make and can | D6: 600 | E6: 1 | F6: Spiritual Energy | G6: Spiritual
A7: 5 | B7: Souls | C7: Souls are a complex thing. Yet, ultimately, quite simple to make. Even the complex souls of people are often created though complete accident. Indeed, a simple object well cared for will eventually gain an identity strong enough to form a soul. You now understand this principle that with sufficient study you can create souls of varying complexity from simple rocks to the intricate existences of people and possibly beyond. | D7: 900 | E7: 1 | F7: Spiritual Energy | G7: Spiritual
A8: 6 | B8: Elementals | C8: Elementals are interesting things. In many ways, they are concepts, enforced onto the world souls that have no need for a form to interact with the world. Though, perhaps because of this, they tend to be... otherwise simple. Still, you understand how to reinforce spiritual structures so that they may influence the wider world without a supporting anchor. | D8: 600 | E8: 1 | F8: Spiritual Energy | G8: Spiritual
A9: 7 | B9: Ichor | C9: Said to be the blood of gods, this material is effectively condensed spiritual energy, rendered into a mores table form. This has a number of uses, though that might require some experimentation for you to uncover | D9: 300 | E9: 1 | F9: Spiritual Energy | G9: Spiritual
A10: 8 | B10: Altar | C10: These devices gather devotion, the deliberate act of sacrifice in order to venerate another, be that of time or something more material. When these acts are performed at an alter, it empowers the souls of the item in question. | D10: 300 | E10: 1 | F10: Divine Insight | G10: Spiritual
A11: 9 | B11: Icon | C11: These devices gather faith, the deep seated belief in the capabilities of something. This empowers that soul to act within the vicinity of the icon, dependent on the belief of the wielder. | D11: 300 | E11: 1 | F11: Divine Insight | G11: Spiritual
A12: 10 | B12: Offering | C12: By preparing an object and ritually destroying it, you can grant strength to the items that you wish to empower. This imbues them with additional spiritual strength, which can be improved by preparing specific offering in line with the soul in question. This also improves the quality of the object to a supernatural degree. | D12: 300 | E12: 1 | F12: Divine Insight | G12: Spiritual
A13: 11 | B13: Pact | C13: A sufficiently powerful soul may grant a portion of it's power to another, bestowing them with a measure of their strength. In doing so however, the recipient is bound to the terms of the transfer. | D13: 600 | E13: 1 | F13: Spiritual Energy | G13: Spiritual
A14: 12 | B14: Demesne | C14: An space claimed by a sufficiently powerful soul can, with time, be suffused with their strength, empowering allies and weakening foes. The strength of this depends of the age of the claim and the power of the soul in question | D14: 300 | E14: 1 | F14: Spiritual Energy | G14: Spiritual
... A23: 21 | B23: Unhallowed Ground | C23: You can prepare a space such that it is inimitable to spiritual presences, and are capable of optimising the effect for specific groups or individual examples for greater effect given sufficient knowledge of them. At a base level, this offers resistance to their influence but can scale to utterly barring them from being able to access the space. | D23: 500 | E23: 1 | F23: Spiritual Energy | G23: Spiritual
A24: 22 | B24: Psionics | C24: The true power of Mind over Matter. Though it is not limited to the realm of the material psionic energy is a manifestation of your inner self on the outside world. This grants basic psionic abilities, though nothing exceptional | D24: 0 | E24: MAX | F24: 0 | G24: Psychic
A25: 23 | B25: WE/YOU/I ARE ONE | C25: Your mind is a part of a greater whole thoughts and beliefs flow in and out. The boundary of your existence if far more permeable than you would have thought and you know how to have your mind reach out, feel and manipulate | D25: 300 | E25: 1 | F25: Psionics | G25: Psychic
A26: 24 | B26: Where Do I End | C26: You are a part of the universe. A part that thinks. But where do you end? You have a command over your existence that most of it does not have, and with the right Will, you may enforce that command over more than thoughts | D26: 300 | E26: 1 | F26: Psionics | G26: Psychic
A27: 25 | B27: Technokinesis | C27: What is technology, but the dreams of people made manifest. Technology has a particular relationship with psionic energies, and you now have the aptitude necessary to directly interface with technology of all kinds with your psychic prowess. | D27: 500 | E27: 1 | F27: Psionics | G27: Psychic
A28: 26 | B28: Thermokinesis | C28: Though some might think of this as pyrokinesis, in truth, this is a broader discipline. Temperature is a fundamental part of reality, and one that you can now exercise some serious control over. | D28: 300 | E28: 1 | F28: Psionics | G28: Psychic
A29: 27 | B29: Photokinesis | C29: Though it may seem as though telekinesis creates energy, that is largely a side effect of the resultant movement. Truly creating energy from psionic power is actually fairly tricky. Still, you now have the aptitude and basic skills necessary to generate bursts of light and even manipulate existing photons through psionic might. | D29: 300 | E29: 1 | F29: Psionics | G29: Psychic
A30: 28 | B30: Electrokinesis | C30: Manipulating something as small and uncertain as electrons requires a delicate touch and a certain mentality that you now possess. Not only are you able to make electrons dance, but you can also generate magnetic fields through will alone. | D30: 300 | E30: 1 | F30: Psionics | G30: Psychic
A31: 29 | B31: Psionic Integration | C31: Psychoactive materials are quite difficult to make, but an integral part of any psionic technology that doesn't involve an ability for self-determination. You gain the fundamental knowledge necessary needed to build psionic devices, including the relevant structural and chemical theory | D31: 300 | E31: 1 | F31: Psionics | G31: Psychic
A32: 30 | B32: Telepathic Interface | C32: Controlling devices with your mind is an interesting prospect, though one that generally requires another mind to link with. With careful application however, you can create a system that operates almost as an extension of the user, receiving and sending telepathic signals that can allow for the use of complex systems | D32: 300 | E32: 1 | F32: Psionic Integration | G32: Psychic
A33: 31 | B33: Telekinetic Arrays | C33: Ah, motive force. The fundamental interface between the now and will be. Producing this through artificial means is the core of creating psionic technology with an ability to impact the physical world. | D33: 300 | E33: 1 | F33: Psionic Integration | G33: Psychic
A34: 32 | B34: Illusionary Systems | C34: Illusions are an interesting aspect of the psionic arts. Though some believe it could be considered an aspect of telepathy, the truth is that illusions are far more complex constructs, capable of programmed action independent of direct control. These psionic constructs can effectively be used as incredibly versatile components that can be altered as necessary | D34: 300 | E34: 1 | F34: Psionic Integration | G34: Psychic
A35: 33 | B35: Mimetic Technology | C35: Ideas are the genetics of civilisation, from opinions to traditions, being able to create mental constructs that spread and persist is both easy and incredibly difficult. Simple earworms are but party tricks compared to what you are capable of. | D35: 500 | E35: 1 | F35: Psionics | G35: Psychic
A36: 34 | B36: Empathic Sensors | C36: Reaching into the subconscious is quite tricky, but necessary for a wide variety of purposes. Through various complex psionic processes, you can create sensors that pick up emotion, desires, intent and all the other underlying currents of the mind | D36: 300 | E36: 1 | F36: Psionic Integration | G36: Psychic
... A43: 41 | B43: Mental Helm | C43: This physical object, when placed in proximity to the seat of consciousness imbues it's wearer with powerful psionic protections, allowing them to shrug off almost any mental intrusion. | D43: 200 | E43: 1 | F43: Psionic Integration | G43: Psychic
A44: 42 | B44: Ki | C44: A mystical energy associated with feats of physical and athletic prowess. This energy grows in response to physical exertion and tends produce results for physical training beyond what would be considered natural. This grants you capabilities equal to an average adept, nothing particularly special, but nothing to be concerned about either | D44: 0 | E44: MAX | F44: 0 | G44: Martial
A45: 43 | B45: Put Your Back Into It | C45: Ki is substance, it is existence. You know how to call upon this energy and put your whole self into everything you do. In addition to magnifying the effects of your actions, it allows you a control over the outcome of your actions beyond what is physically possible. | D45: 300 | E45: 1 | F45: Ki | G45: Martial
A46: 44 | B46: Martial Reinforcement | C46: You know how to flow your Ki into objects you wield making them more durable and effective. You skill in this grows with time and power, but even initially, you can empower swords enough to cut through wooden posts without so much as dulling the blade. | D46: 300 | E46: 1 | F46: Ki | G46: Martial
A47: 45 | B47: Legendary Smith | C47: Your works are just better. Better than they have any right to me. Perhaps it is the ki adding more than strength to your blows, producing works that are orders of magnitude more capable than they really should be. | D47: 300 | E47: 1 | F47: Ki | G47: Martial
A48: 46 | B48: Beat it into Them | C48: Demonstrating, but the real way to learn how to fight is to fight. You can train people incredibly quickly through a combination of demonstration and sparring forcing proper form and technique into the minds of your students | D48: 300 | E48: 1 | F48: Ki | G48: Martial
A49: 47 | B49: Attuned Tools | C49: It normally takes years to get used to a tool, to know it as you know yourself. However, with sufficient skill a craftsman can create a tool designed for a single person, allowing them to wield it with such ease that it is better than anything else comparable would be in their hands and take to Ki augmentation particularly well | D49: 300 | E49: 1 | F49: Ki | G49: Martial
A50: 48 | B50: Prized Bloodline | C50: Certain fighters have specific talents, born of pure chance or breeding programs that might have gone on for generations. Not only can you identify the martial talents put in front of you, you can also isolate and replicate these factors in others | D50: 300 | E50: 1 | F50: Ki | G50: Martial
A51: 49 | B51: Strict Diet | C51: You are what you eat. Not only do you know what food is best for what purposes, but based on the resources you have available to you, you also know how to create the optimal possible diet for any given outcome, significantly accelerating progress. This also works for abnormal nutrition requirements like specific kinds of blood for vampires or alternative fuel sources for androids | D51: 300 | E51: 1 | F51: Ki | G51: Martial
A52: 50 | B52: Technique Scrolls | C52: Getting the intricacies of martial technique to survive you is tricky. Martial arts is not often best described by words and pictures. But you can do it. In fact, you know exactly how to produce instructional materials of all kinds that are incredibly instructive items capable of perfectly pouring knowledge into even the poorest of pupils | D52: 300 | E52: 1 | F52: 0 | G52: Martial
A53: 51 | B53: Strange Concoctions | C53: These substances work far better than they should. Taking advantage of the supernatural qualities of Ki, these substances are able to perform feats that could be considered miraculous. They can cure mortal wounds, grant immense stamina or incredible strength or speed | D53: 400 | E53: 1 | F53: Ki | G53: Martial
A54: 52 | B54: Extreme Training | C54: Ki makes things that might seem impractical entirely possible. Be it carrying around massive rocks, or dodging arrows blindfolded, you know how to get extreme results from extreme effort, the more extreme the better | D54: 500 | E54: 1 | F54: Ki | G54: Martial
A55: 53 | B55: Training Grounds | C55: You know how to organize a space in such a way that it is perfect for particular uses, to a supernatural degree. Through the careful application of Ki and the flows of energy, you can create spaces that accelerate training or indeed any other specific activity | D55: 400 | E55: 1 | F55: 0 | G55: Martial
A56: 54 | B56: Animalistic Skill | C56: It is said that the old masters learned to fight by observing the movements of animals, producing various schools of martial arts. At their height these warriors were capable of nearly magical feats, replicating the inhuman capabilities of these creatures. With study and training, you can now also replicate some of the physical feats of these creatures. | D56: 500 | E56: 1 | F56: Ki | G56: Martial
A57: 55 | B57: Honor Vow | C57: There are ways to… concentrate your existence. To focus your presence. Even without supernatural influence dedication has its effects. With Ki, however, this effect is magnified, not only providing you a general bonus as you hold to the terms of your oath, but also significantly increasing your capabilities as you close in on the target of your Vow | D57: 300 | E57: 1 | F57: Ki | G57: Martial
A58: 56 | B58: Conservation of Ninjutsu | C58: The faceless, diffuse actions of a mass of efforts, often not entirely aligned means that only so much force can be brought against a single foe. You now have the stamina and strength to take advantage of those gaps in co-ordination. As the number of enemies grows the more of these gaps exist and the easier you find the fight. | D58: 750 | E58: 1 | F58: 0 | G58: Martial
A59: 57 | B59: Berserker State | C59: Through careful training, the matter of Fight and Flight is answered. In various situations, you can call upon a deep reserve of power and durability able to act unfettered by any injury and disregard any pain you may be in. | D59: 1000 | E59: 1 | F59: Ki | G59: Martial
A60: 58 | B60: Vital Spirit | C60: There are limits to power, ends to your strength, but sometimes you need to push past it, regardless of the cost. There are limitations built into any mortal form. And there are ways to push past them. You can effectively 'cast from hit points' empowering your other abilities at the cost of damaging yourself. | D60: 500 | E60: 1 | F60: 0 | G60: Martial
A61: 59 | B61: Final Breath | C61: In one final gasp, in an exertion where you have nothing to loose, you can draw upon the last dregs of your strength with utter abandon, increasing your capabilities by orders of magnitude for a short period, though this does significantly damage your portal form. Even the greatest means of resurrection will have challenges undoing the harm done to yourself. | D61: 500 | E61: 1 | F61: Ki | G61: Martial
A62: 60 | B62: Accelerated Recovery | C62: You know how to call upon your Ki in such a way that it accelerates the process of healing while not only retaining but even improving the benefits of such exertion. Your body adapts to strain more quickly and without issue. | D62: 400 | E62: 1 | F62: Ki | G62: Martial
A63: 61 | B63: Mirror Moves | C63: An enemy can be the best teacher sometimes, and when it comes to you, that is most definitely true. You easily pick up moves, tricks and skills used against you, identifying them almost immediately and only needing another one or two examples to fully internalise it. | D63: 200 | E63: 1 | F63: 0 | G63: Martial
A64: 62 | B64: C-C-C-Counter! | C64: The limitations of the physical form cannot be overcome through skill alone, and there are always compromises to be made. Compromises that you can easily identify. From even a single example, you know what you need to do in order to counter any specific move of means of attack, though leveraging that information is a matter of your own skills. | D64: 200 | E64: 1 | F64: 0 | G64: Martial
A65: 63 | B65: Perfect Flow | C65: Skill in battle is not just about what you know, but how you put it into practice. You have a particular talent for efficiency, able to efficiently execute your intended movements without a single wasted calorie of effort. This carries over into the rest of your life, granting you a certain undeniable presence. | D65: 200 | E65: 1 | F65: 0 | G65: Martial
A66: 64 | B66: Alchemic Symbols | C66: There are patterns, esoteric symbols that form the basis of alchemy. They require not particular affinity, merely knowledge of their function and the right training in order to enact simple instantaneous effects. You can receive this perk up to five times, the first granting your access to the core four (disintegration, cleansing, assembly and stasis), the next granting you effigies of the states of matter and energy (solid, liquid, gas, plasma etc and heat, mass, light etc). The third grants you access to the four base conceptual elements (fire, water, earth, air) and the fourth grants you the Unreal Words (spirit, thought, motion, divinity, stories, ideas etc). The last, however, grants you every remaining word allowing you to describe anything in alchemical terms. | D66: 400 | E66: 5 | F66: 0 | G66: Alchemy
A67: 65 | B67: Transmutation Arrays | C67: These complex arrangements of alchemical symbols allow you to enact various alchemical processes in such a way that you can chain together a series of symbols representing various items in order to enact transmutations, alchemical processes that transform items. The first time you receive this perk your main focus is in altering the structure of items, retaining the same materials. The next allows you some control over their form, allowing you to transform items into other things so long as they are generally similar. The last stage grants you sufficient understanding to reduce objects their base materials and reconstruct them into entirely new forms. | D67: 300 | E67: 3 | F67: Alchemic Symbols | G67: Alchemy
A68: 66 | B68: Destruction | C68: This grants you a deep understanding of the fundamental concept of destruction, the ability to render something down to parts and components. | D68: 300 | E68: 1 | F68: 0 | G68: Alchemy
A69: 67 | B69: Purification | C69: You gain an intuitive understanding of the process of purification, of how to remove impurities from any substance, returning it to a pure state. | D69: 300 | E69: 1 | F69: 0 | G69: Alchemy
A70: 68 | B70: Construction | C70: You know how to combine various materials in order to create complex substances, allowing you to create new materials and mechanisms that allow you greater flexibility. | D70: 300 | E70: 1 | F70: 0 | G70: Alchemy
A71: 69 | B71: Stability | C71: You know how to finish an alchemical process, rendering the result of your works as permanent as if the product was natural. A Stable alchemical creation is as real as any natural equivalent | D71: 300 | E71: 1 | F71: 0 | G71: Alchemy
A72: 70 | B72: Elixir of Life | C72: You know how to create an alchemical substance that can de-age living things, extending their lifespan. This requires difficult to get ingredients and is a complex process even for the best alchemists. | D72: 500 | E72: 1 | F72: 0 | G72: Alchemy
A73: 71 | B73: Panacea | C73: You know how to create an alchemical substance that can heal any injury or cure any disease. It is very difficult to make, even for the greatest alchemists and requires rare ingredients. | D73: 500 | E73: 1 | F73: 0 | G73: Alchemy
A74: 72 | B74: Philosopher Stone | C74: You know how to suspend the alchemical process, producing a stable energy that can act as a universal source for any alchemical process. This can even substitute for some of the ingredients of complex alchemical works. | D74: 750 | E74: 1 | F74: 0 | G74: Alchemy
A75: 73 | B75: The Great Work | C75: You know how to alter the very fundamentals of reality, refining objects in such a way as they are more perfect in some way, approaching the conceptual ideal of what it means to be that object. This allows them to act more effectively when used for their intended purposes. | D75: 1000 | E75: 1 | F75: 0 | G75: Alchemy
A76: 74 | B76: Atomic Synthesis | C76: You know how to bypass the usual material constraints of Alchemy, transforming the vary materials that compose physical items. By breaking things down to the subatomic level, you can reassemble the building blocks into new elements and substances. | D76: 500 | E76: 1 | F76: 0 | G76: Alchemy
A77: 75 | B77: Automated Alchemy | C77: Alchemy is normally a manual process, involving the direct intervention of the alchemist in question. However, you know how to account for every stage of the transmutation, allowing them to be operate entirely independently. | D77: 750 | E77: 1 | F77: Transmutation Arrays | G77: Alchemy
A78: 76 | B78: Chimeric Creations | C78: Given the complex nature of living systems, working with them in alchemical procedures is always a challenge. However, it is possible to treat living components as something of a black box, combining them to other systems through alchemical processes. Though this can be a little... crude in appearance. | D78: 400 | E78: 1 | F78: Alchemic Symbols | G78: Alchemy
A79: 77 | B79: Living Alchemy | C79: Life is extremely difficult to effect through alchemical processes. As a complex and chaotic environment, working any alchemy on a living thing is incredibly difficult, but you now understand how to account for these things, allowing you to heal and otherwise manipulate a body. | D79: 350 | E79: 1 | F79: Alchemic Symbols | G79: Alchemy
A80: 78 | B80: Homunculi | C80: Creating animate objects is considered one of the greater alchemical feats. And it is one that you are now capable of. Though this does not grant the knowledge required to produce minds with true intelligence, you can encode any form of logic you can understand. | D80: 500 | E80: 1 | F80: Alchemic Symbols | G80: Alchemy
A81: 79 | B81: Bloodline Transmutation | C81: You know how to embed alchemical understanding into the very essence of beings. This enable the being to more easily enact alchemical processes that involve this knowledge. However, the difficulty increases with the scope of the knowledge inserted. Most beings have trouble holding more than a single secret. | D81: 300 | E81: 1 | F81: Alchemic Symbols | G81: Alchemy
A82: 80 | B82: Simplified Transmutation | C82: You know how to reduce the usually complicated process associated with alchemy into much simpler forms. Indeed, some processes can be reduced to such a level that they can be held entirely in the mind, allowing a person to enact transmutations without external aid. | D82: 500 | E82: 1 | F82: Transmutation Arrays | G82: Alchemy
A83: 81 | B83: Complex Creations | C83: You know how to encode extremely complex structural information into your alchemical processes, allowing you to produce complex items such as machines with many moving and independent parts. | D83: 300 | E83: 1 | F83: Alchemic Symbols | G83: Alchemy
A84: 82 | B84: Alchemic Reversion | C84: Though it may seem that alchemical transmutations are perfect, you know how to pick at the seams of such things, allowing you to reverse various alchemical processes. Though, some are easier than others. The quality of the transmutation factors heavily into how perfectly something has been altered and thus the difficulty in reversing any such changes. | D84: 1200 | E84: 1 | F84: Alchemic Symbols | G84: Alchemy
A85: 83 | B85: Magic | C85: The ultimate expression of mysticism, this grants you a supply of that arcane energy that is permits so many forms of supernatural capabilities. Though you are no archmage, your capabilities are not weak either. This grants you the power of a middling mage, capable of learning most spells. | D85: 0 | E85: MAX | F85: 0 | G85: Magic
A86: 84 | B86: Wishes and Dreams | C86: Magic, ultimately is about belief. It is about effect following cause, even when the physical realities don't align. From the greatest rituals to the least cantrip, it is this foundation that persists, and one that you understand on a fundamental level | D86: 300 | E86: 1 | F86: Magic | G86: Magic
A87: 85 | B87: Enchanting | C87: Magic is effect. It is the result of arcane intention enforced unto reality. So often that means that it is transient, ephemeral. But you know how to bind it. Though thematic substrates will make it easier, you are able to bind a mystical effect to any item and engage the result repeatedly though perhaps with a cooldown depending on the scale of the effect. | D87: 600 | E87: 1 | F87: Magic | G87: Magic
A88: 86 | B88: Arcane Focus | C88: Manipulating magic takes imagination, focus, knowledge and power. While some things are dependent on the wielder you can make it easier to focus, at least. From augmenting a mage's focus directly or simply offloading some of the strain, you know how to make tools that ease the process of performing arcane acts. | D88: 200 | E88: 1 | F88: Magic | G88: Magic
A89: 87 | B89: Potioncraft | C89: Ah, those flasks of mysterious fluid all sitting pretty on the shelf. You know the intricacies of how ingredients interact and the subtle power that lies within a cauldron. You know what ingredients can be substituted for each other and how call the sparks of magic from what seems like mundane materials. | D89: 300 | E89: 1 | F89: Magic | G89: Magic
A90: 88 | B90: Rituals | C90: Grand desires often entail grand action. This is true in magic just as it is in other ventures. Through sacrifice both material and symbolic you know how to vastly increase the scale at which your magic can function. | D90: 600 | E90: 1 | F90: Magic | G90: Magic
A91: 89 | B91: Geomancy | C91: Ley Lines, Genus Loci, Places of Power... all of these have immense arcane might that you can turn to your ends. You can manipulate and even create these artefacts. | D91: 900 | E91: 1 | F91: Rituals | G91: Magic
A92: 90 | B92: Divination | C92: To be a wizard, witch or even sorcerer is to be someone with wisdom or knowledge beyond common ken. And magic has many ways of gathering that information. You have a talent for various forms of divination - that inner eye that you can hone with sufficient practice | D92: 550 | E92: 1 | F92: Magic | G92: Magic
A93: 91 | B93: Grimoire | C93: Simply storing arcane lore is difficult, knowledge is power and powerful magic is often not particularly predictable. You however, know how to encode magical secrets in a manner that is safe and understandable, allowing you to ease the process of working complex acts. These methods also happen to be great at handling all kinds of exotic knowledge. | D93: 400 | E93: 1 | F93: Magic | G93: Magic
A94: 92 | B94: Portals | C94: Being able to access distant locales has always been a dream of mages, and is particularly useful when it comes to transporting large amounts of material or people. This ritual can be customised to produce a portal of any shape, size or duration to a destination you can adequately describe, though as those factors become greater, harder to describe or encounter various obstacles (even simple distance), the difficulty of the ritual and the quality of the required reagents increase. | D94: 300 | E94: 1 | F94: Enchanting | G94: Magic
A95: 93 | B95: Teleportation | C95: You are here, and now you are not. You now have knowledge of a spell that allows you to teleport yourself, and sufficient understanding to alter it to affect others and even groups, though that increases the cost and complexity. | D95: 200 | E95: 1 | F95: Wishes and Dreams | G95: Magic
A96: 94 | B96: Fated Blow Enchantment | C96: You know how to enchant projectile weapons such that they will always hit their target. From named bullets to spears that would weave around obstacles, this enchantment can be tweaked and optimised for a variety of expressions. | D96: 250 | E96: 1 | F96: Enchanting | G96: Magic
A97: 95 | B97: Elemental Enchantment | C97: You can enchant objects in such a way so as to have them generate effects aligned with various elements, and can fine tune the expression to take on various forms. From blades that can send out blades of razor-sharp wind to hammers that shatter the earth, this can take on a vast variety of forms. | D97: 100 | E97: 1 | F97: Enchanting | G97: Magic
... A105: 103 | B105: Mystic Materials | C105: Magic can bring out all sorts of strange properties in otherwise mundane materials. While this is usually due to complex natural processes, you know how to precipitate magic in the structure of previously mundane materials resulting in permanent transformations as magic becomes a permanent part of their existence. | D105: 300 | E105: 1 | F105: Wishes and Dreams | G105: Magic
A106: 104 | B106: Eldritch Mind | C106: Some people say that there are things that mortals were not meant to know. You disagree, sometimes it just takes a special mind. And you happen to have one such mind, capable of handling even the most unnatural of thoughts | D106: 0 | E106: 1 | F106: 0 | G106: Eldritch
A107: 105 | B107: Equivalence | C107: It's all the same at the end of the day. Everything at the most base level is energy, and were all once part of a greater whole. You know how to reach back to that primordial state and convert one from of energy into another. | D107: 600 | E107: 1 | F107: 0 | G107: Eldritch
A108: 106 | B108: Though the Dreamer Wakes | C108: The world may be a dream, you are not... or are you? Perhaps you are simply a thought, some persistent whisper in the minds of the grand cosmic existence. Whatever it is, you can persist past the end of the universe, and await the birth of the next. | D108: 750 | E108: 1 | F108: Eldritch Mind | G108: Eldritch
A109: 107 | B109: Strange Angles | C109: You know there is more to the world that others see, layers and angles to eternity. Strange Places where wrong is right, where shadows are cast over eternal light. Though they may seem as dreams you know what lays beyond the world's seams. | D109: 500 | E109: 1 | F109: Eldritch Mind | G109: Eldritch
A110: 108 | B110: Nothing but a shadow | C110: We are but shadows of something great, a soul perhaps or some other state. There is more than up and down, left or right. There are things move beyond the night. | D110: 500 | E110: 1 | F110: Eldritch Mind | G110: Eldritch
A111: 109 | B111: When the stars are right | C111: The universe extends into places unknown, with existence itself weighing it down. What waters lay at the bottom of gravity wells? A paradise perhaps or unknown hells. When the stars align, streams combine. Trickles gather into torrents and with eerie portents, mysterious machines enact strange schemes. | D111: 500 | E111: 1 | F111: Cosmic Wells | G111: Eldritch
A112: 110 | B112: Strange Places | C112: There are strange places in the world, where doors do not lead where you expect and distances seem inconsistent. Where even trying to map them out can lead to madness. Some are natural, others are not and now you know how to create them. | D112: 250 | E112: 1 | F112: Eldritch Mind | G112: Eldritch
A113: 111 | B113: Eldritch Tongues | C113: There are many languages that mere mortals cannot properly speak, or on some cases understand. Vocalisations beyond the capabilities of lesser beings. That limitation does not apply to you. Not only can you generate any noise that you wish but you can also decipher any language - spoken, written, signed or otherwise communicated - but you also learn them incredibly quickly. As a side effect you can also learn any mortal language with a few hours of exposure and mimic and voice or accent after a few minutes. | D113: 200 | E113: 1 | F113: Eldritch Mind | G113: Eldritch
A114: 112 | B114: An extrusion | C114: The forms that cosmic forces take on in the mortal realm are not their true selves. Such things are too great to exist without destroying existence. Instead, they are extrusions, miniscule fragments of their power, like the end of a pair of tweezers poking at reality. You can now replicate this feat, retracting the majority of your existence into yourself and exposing only what you wish. Should you be strong and mentally powerful enough, you might even be able to summon multiple such extrusions. | D114: 350 | E114: 1 | F114: Eldritch Mind | G114: Eldritch
A115: 113 | B115: Laws | C115: You know how to create spaces with altered physical laws, through the manipulation of the Aether, you can effectively create spaces where the natural laws are something other than the familiar physics of your universe. | D115: 1200 | E115: 1 | F115: Aether | G115: Eldritch
A116: 114 | B116: Cosmic Wells | C116: Beneath all of existence, there exist infinities unseen. There are ways to pierce the limited illusion of existence, calling forth power from beyond what mere mortals are able to comprehend. This can be turned to a variety of ends, though the simplest would be in the form of light and heat. | D116: 400 | E116: 1 | F116: 0 | G116: Eldritch
A117: 115 | B117: Servitors | C117: Sometimes greater forces cannot act on such miniscule levels, and thus have need of tools with a certain… delicacy. You understand how to replicate these processes, creating constucts with strange capabilities, some that may seem fantastical to your average mortal. | D117: 350 | E117: 1 | F117: 0 | G117: Eldritch
A118: 116 | B118: Altered Existence | C118: Such menial beings cannot withstand the presence of a greater power. And now that you know how to summon those forces, you can raise these pathetic mortals into something more worthwhile. These new creatures can be stronger, faster, more long lived though may be effected in other ways in a much less predictable manner. | D118: 200 | E118: 1 | F118: Eldritch Mind | G118: Eldritch
A119: 117 | B119: A Calling | C119: Your name is special… No, not your common name. Your full name. You have gained a title, which forms the basis of an Invocation. To use this is to refer to you, and you are aware, to an extent of when it is used. However, when this title is used in conjuction with other ways to identify you (other titles or even your personal name) this becomes a true Calling. A means of granting you awareness of the situation in which you have been invoked. | D119: 300 | E119: 1 | F119: Eldritch Mind | G119: Eldritch
A120: 118 | B120: Beneath Notice | C120: Mere mortals are to cosmic forces less than the least speck of dust is to them. While unsettling, this does have it's advantages, and you can extend these advantages to other levels of existence, rendering yourself so utterly beneath notice that you are effectively undetectable. | D120: 750 | E120: 1 | F120: Eldritch Mind | G120: Eldritch
A121: 119 | B121: Warding Glyph | C121: You can place a glyph, a simple two dimensional shape that extends into higher dimensions. This produces an unpleasant sensation that can effect even Higher Beings, encouraging them to avoid the area. This is not a true defense, however, as it will cruble against any focused effort. | D121: 100 | E121: 1 | F121: 0 | G121: Eldritch
...
